setup.py
tapioca_instagram/__init__.py
tapioca_instagram/resource_mapping.py
tapioca_instagram/tapioca_instagram.py
tapioca_instagram.egg-info/PKG-INFO
tapioca_instagram.egg-info/SOURCES.txt
tapioca_instagram.egg-info/dependency_links.txt
tapioca_instagram.egg-info/not-zip-safe
tapioca_instagram.egg-info/requires.txt
tapioca_instagram.egg-info/top_level.txt