Metadata-Version: 1.1
Name: tapioca-instagram
Version: 0.2
Summary: Instagram API wrapper using tapioca
Home-page: https://github.com/vintasoftware/tapioca-instagram
Author: Anderson Resende
Author-email: andersonresende86@gmail.com
License: MIT
Keywords: instagram
Platform: UNKNOWN
Classifier: Development Status :: 5 - Production/Stable
Classifier: Intended Audience :: Developers
Classifier: License :: OSI Approved :: MIT License
Classifier: Natural Language :: English
Classifier: Programming Language :: Python :: 2
Classifier: Programming Language :: Python :: 2.7
Classifier: Programming Language :: Python :: 3
Classifier: Programming Language :: Python :: 3.1
Classifier: Programming Language :: Python :: 3.2
Classifier: Programming Language :: Python :: 3.3
Classifier: Programming Language :: Python :: 3.4
